{
  "generated_at": "2026-04-15T00:48:05.576264+00:00",
  "status": "pass",
  "check_count": 30,
  "error_count": 0,
  "checks": {
    "finance-openclaw-runtime-contract.md:exists": true,
    "finance-openclaw-runtime-contract.md:contains:typed EvidenceRecord / ContextPa": true,
    "finance-openclaw-runtime-contract.md:contains:JudgmentEnvelope": true,
    "finance-openclaw-runtime-contract.md:contains:finance_decision_report_render.p": true,
    "finance-openclaw-runtime-contract.md:contains:finance_report_product_validator": true,
    "finance-openclaw-runtime-contract.md:contains:finance_decision_log_compiler.py": true,
    "finance-openclaw-runtime-contract.md:contains:finance_report_delivery_safety.p": true,
    "finance-openclaw-runtime-contract.md:contains:Compatibility Surfaces": true,
    "finance-report-contract.md:exists": true,
    "finance-report-contract.md:contains:ContextPacket": true,
    "finance-report-contract.md:contains:WakeDecision": true,
    "finance-report-contract.md:contains:JudgmentEnvelope": true,
    "finance-report-contract.md:contains:finance-decision-report-envelope": true,
    "finance-report-contract.md:contains:compatibility mirror": true,
    "finance-gate-taxonomy.md:exists": true,
    "finance-gate-taxonomy.md:contains:Market Candidate Gate": true,
    "finance-gate-taxonomy.md:contains:Wake / Dispatch Gate": true,
    "finance-gate-taxonomy.md:contains:Judgment Gate": true,
    "finance-gate-taxonomy.md:contains:Product Report Gate": true,
    "finance-gate-taxonomy.md:contains:Decision Log / Delivery Safety G": true,
    "operating-model.md:exists": true,
    "operating-model.md:contains:Authority Order": true,
    "operating-model.md:contains:Benchmark Boundary": true,
    "operating-model.md:contains:Review-Only Safety": true,
    "finance-openclaw-runtime-contract.md:banned-active-claim:1": true,
    "finance-openclaw-runtime-contract.md:banned-active-claim:2": true,
    "finance-report-contract.md:banned-active-claim:1": true,
    "finance-report-contract.md:banned-active-claim:2": true,
    "finance-gate-taxonomy.md:banned-active-claim:1": true,
    "finance-gate-taxonomy.md:banned-active-claim:2": true
  },
  "errors": []
}
